{
  "url": "http://77.42.251.205/LawView.aspx?opt=view&LawID=178368",
  "title": "يختص  بالرواتب  الجديدة المعطاة للقضاة الافرنسيين\r\nالمستخدمين في لبنان",
  "metadata": {
    "type": "تعريف النص: مرسوم",
    "number": "8025",
    "date": " 16/05/1931",
    "oj_number": "2505",
    "oj_publish_date": "27/05/1931",
    "oj_page": "3"
  },
  "preamble": "",
  "articles": [
    {
      "number": "2 \r\nمادة 2:\r\nيبلغ هذا المرسوم حيث  تدعو الحاجة الى ذلك",
      "content": [
        {
          "type": "text",
          "data": "مادة 1:\r\nيعطى القضاة الافرنسيون المستخدمون في لبنان حق الاستفادة\r\nمن الرواتب  الجديدة الورادة في المادة التاسعة والذيل 1 من\r\nقرار المفوضية العليا عدد R/25 المؤرخ في 2 نيسان سنة 1931\r\nاعتبارا من 3 شباط سنة 1930"
        }
      ]
    },
    {
      "number": "1",
      "content": [
        {
          "type": "text",
          "data": "مادة 2:\r\nيبلغ هذا المرسوم حيث  تدعو الحاجة الى ذلك"
        }
      ]
    }
  ],
  "signature": "بيروت  في 16 ايار سنة 1931\nالامضاء: شارل دباس\nصدر عن رئيس  الجمهورية\nرئيس  مجلس  الوزراء وزير المالية والزراعة\nالاضماء: اوغست  اديب\nوزير العدلية\nالامضاء: احمد الحيسني"
}