{
  "url": "http://77.42.251.205/LawView.aspx?opt=view&LawID=181644",
  "title": "يتضمن التعديل رقم 18 لتعريفة الجمارك",
  "metadata": {
    "type": "تعريف النص: قرار",
    "number": "1035",
    "date": " 06/01/1961",
    "oj_number": "3",
    "oj_publish_date": "18/01/1961",
    "oj_page": "41-42"
  },
  "preamble": "",
  "articles": [
    {
      "number": "2 \r\nمادة 2:\r\nيعمل بهذا القرار وفقا لقانون الجمارك وخاصة المواد 13 و14\r\nو16 منه وينشر ويبلغ حيث  تدعو الحاجة.",
      "content": [
        {
          "type": "text",
          "data": "مادة 1:\r\nتعدل تعرفة الجمارك على الوجه التالي:\r\nرقم              بيان الاصناف          اسم    معدل الرسم في\r\nالبند                                 الرسم      التعريفة\r\n                                                 العادية"
        },
        {
          "type": "text",
          "data": "68/12   مصنوعات  من خليط حرير صخري\r\n        (اميانت ) باسمنت  او بمواد تماسك\r\n        اخرى, مصنوعات  من خليط الياف\r\n        سليلوز باسمنت  او بمواد تماسك\r\n        اخرى ومصنوعات  مماثلة:\r\n        آ- قساطل, الواح, مربعات ,\r\n        الواح معدة لتغطية السطوح       القيمة       50%\r\n        ب - (دون تعديل)"
        }
      ]
    },
    {
      "number": "1",
      "content": [
        {
          "type": "text",
          "data": "مادة 2:\r\nيعمل بهذا القرار وفقا لقانون الجمارك وخاصة المواد 13 و14\r\nو16 منه وينشر ويبلغ حيث  تدعو الحاجة."
        }
      ]
    }
  ],
  "signature": "بيروت  في ك2 سنة 1961\nالرئيس\nالامضاء: جورج حيمري\nالعضو               العضو\nالامضاء: حسين العبدالله  الامضاء: احسان بيضون"
}