{
  "url": "http://77.42.251.205/RulingView.aspx?opt&RulID=79606",
  "title": ":: الجامعة اللبنانية - مركز الدراسات القانونية ::الأحكام ::  رؤية الحكمتمييز جزائي حكم رقم : 28 /2006",
  "card_info": {
    "court": "تمييز جزائي",
    "number": "28",
    "year": "2006",
    "session_date": "25/01/2006",
    "chief": "عفيف شمس الدين",
    "members": "/حيدر//مكي/"
  },
  "ruling_text": "ان موضوع التمييز هو دفع شكلي، وبالتالي يكون مقبولا شكلا سندا للمادتين 311 و318 اصول المحاكمات الجزائية.\nان الدفع بعدم اختصاص القضاء الجزائي بسبب مدنية النزاع لا يعتبر دفعا شكليا بحسب مفهوم المادة 73 اصول المحاكمات الجزائية، وانما دفاعا باساس الدعوى يستوجب للبت به اجراء التحقيقات الوصول الى تحديد طبيعة النزاع. يرد الدفع المدلى به.\nان الدفع بانتفاء الجرم الجزائي ليس صحيحا، اذ ان الجرائم المدعى بها هي الاحتيال والتزوير وهي في حال ثبوتها تشكّل جرائم جزائية معاقب عليها قانونا. يرد الدفع لعدم صحته."
}