{
  "url": "http://77.42.251.205/LawView.aspx?opt=view&LawID=213476",
  "title": "ترخيص جمعية رياضية باسم «نادي أكوا مارينا الرياضي»",
  "metadata": {
    "type": "تعريف النص: قرار",
    "number": "39",
    "date": " 20/03/2006",
    "oj_number": "18",
    "oj_publish_date": "06/04/2006",
    "oj_page": "1930-1931"
  },
  "preamble": "إن وزير الشباب والرياضة،\nبناء على المرسوم رقم 14953 تاريخ 19/7/2005 (تشكيل الحكومة)،\nبناء على القانون رقم 247 تاريخ 7/8/2000 (دمج وإلغاء وإنشاء وزارات ومجالس)،\nبناء على القانون رقم 629 تاريخ 20/1/2004 (تنظيم وزارة الشباب والرياضة)،\nبناء على المرسوم 6997 تاريخ 24/12/2001 (تحديد الشروط التي تخضع لها جمعيات الشباب والرياضة والكشافة)،\nبناء على طلب الترخيص المقدم من الهيئة التأسيسية لجمعية «نادي أكوا مارينا الرياضي» المسجل تحت الرقم 544/د تاريخ 22/2/2005،\nبعد موافقة وزارة الداخلية والبلديات بكتابها رقم 23244 تاريخ 18/2/2006،\nبناء على تقرير الكشف الميداني على منشآت الجمعية بتاريخ 8/3/2006،\nبناء على اقتراح المدير العام للشباب والرياضة،\nيقرر ما يأتي:",
  "articles": [
    {
      "number": "5 مادة 5:\r\nينشر هذا القرار في الجريدة الرسمية وفي وسيلة إعلامية أخرى، على نفقة المؤسسين، ويعمل به فور نشره، ويبلغ حيث تدعو الحاجة.",
      "content": [
        {
          "type": "text",
          "data": "مادة 1:\r\nيرخص بتأسيس جمعية رياضية باسم: «نادي أكوا مارينا الرياضي».\r\nـ مركزها: كفر ياسين، قضاء كسروان، محافظة جبل لبنان.\r\nـ الألعاب المرخص بها: سباحة."
        }
      ]
    },
    {
      "number": "1",
      "content": [
        {
          "type": "text",
          "data": "مادة 2:\r\nتتألف الهيئة التأسيسية للجمعية من السادة:\r\nسابين الياس عبد النور، رشيد شفيق سركيس، فادي فيليب سعادة، حبيب مسعود رحمة، جورج الياس خوام، سمعان جرجس الدويهي، سوزان فنسان عطية."
        }
      ]
    },
    {
      "number": "2",
      "content": [
        {
          "type": "text",
          "data": "مادة 3:\r\nتمارس الهيئة التأسيسية صلاحيات الهيئة الادارية وتحدد مدة ولايتها بسنتين على الاكثر من تاريخ صدور هذا القرار."
        }
      ]
    },
    {
      "number": "3",
      "content": [
        {
          "type": "text",
          "data": "مادة 4:\r\nعلى الجمعية المذكورة التقيد بالأنظمة والقوانين المرعية الإجراء، والانضمام إلى اتحاد اللعبة المذكورة أعلاه خلال ستة أشهر من تاريخ صدور هذا القرار، وفي حال عدم الانضمام خلال هذه المهلة يعتبر هذا الترخيص ملغى."
        }
      ]
    },
    {
      "number": "4",
      "content": [
        {
          "type": "text",
          "data": "مادة 5:\r\nينشر هذا القرار في الجريدة الرسمية وفي وسيلة إعلامية أخرى، على نفقة المؤسسين، ويعمل به فور نشره، ويبلغ حيث تدعو الحاجة."
        }
      ]
    }
  ],
  "signature": "بيروت في 20 آذار 2006\nوزير الشباب والرياضة\nد. أحمد فتفت"
}