{
  "url": "http://77.42.251.205/RulingView.aspx?opt&RulID=80646",
  "title": ":: الجامعة اللبنانية - مركز الدراسات القانونية ::الأحكام ::  رؤية الحكممحكمة الجنايات حكم رقم : 310 /2013",
  "card_info": {
    "court": "محكمة الجنايات",
    "number": "310",
    "year": "2013",
    "session_date": "15/03/2013",
    "chief": "فيصل حيدر",
    "members": "/الخوري//القسيس/"
  },
  "ruling_text": "يجرم المتهم بجناية المادة 459/219 عقوبات لاقدامه على الاستحصال على افادة عقارية مزورة ووكالة رسمية ببيع العقار وعلى استعمال المزور سندا للمادة 459/454 عقوبات ببيع العقار الى المدعية.\nيدان المتهم بجنحة المادة 463/219 عقوبات لاقدامه على الاستحصال على اخراج قيد مزور واستعماله سندا للمادة 463/454/219 عقوبات للاستحصال على وكالة مزورة ببيع العقار من المدعية لابتزاز اموالها فيدان بجنحة الاحتيال المنصوص عليها في المادة 655 عقوبات. ويعود للمحكمة حق تقدير ثبوت الجرم بحق المتهم وتحديد التعويض للمدعية التي اشترت العقار بموجب وكالة البيع المزورة."
}