{
  "url": "http://77.42.251.205/LawView.aspx?opt=view&LawID=166263",
  "title": "دعوة مجلس النواب الى عقد استثنائي",
  "metadata": {
    "type": "تعريف النص: مرسوم",
    "number": "46",
    "date": " 30/12/1998",
    "oj_number": "1",
    "oj_publish_date": "07/01/1999",
    "oj_page": " 2-3"
  },
  "preamble": "ان رئيس الجمهورية,\nبناء على الدستور لا سيما المادتان 33\nو86 منه,\nبناء على اقتراح رئيس مجلس الوزراء,\nيرسم ما يأتي:",
  "articles": [],
  "signature": "بعبدا في 30 كانون الاول 1998\nالامضاء: اميل لحود\nصدر عن رئيس الجمهورية\nرئيس مجلس الوزراء\nالامضاء: سليم الحص\nرئيس مجلس الوزراء\nالامضاء: سليم الحص"
}