{
  "url": "http://77.42.251.205/LawView.aspx?opt=view&LawID=244377",
  "title": "تنظيم منح رخص  بيع التبغ والتنباك",
  "metadata": {
    "type": "تعريف النص: قرار",
    "number": "2401",
    "date": " 26/07/1960",
    "oj_number": "33333",
    "oj_publish_date": "03/08/1960",
    "oj_page": "792-799"
  },
  "preamble": "نعم",
  "articles": [
    {
      "number": "9  ينشر هذا القرار في الجريدة الرسمية ويطبق ابتداء من اول تموز سنة 1960",
      "content": [
        {
          "type": "text",
          "data": "تقسم مدينة بيروت الى ثلاث مناطق:"
        },
        {
          "type": "text",
          "data": "1) المنطقة الممتازة وهي تشمل:"
        },
        {
          "type": "text",
          "data": "- ساحة الدباس"
        },
        {
          "type": "text",
          "data": "- ساحة الشهداء"
        },
        {
          "type": "text",
          "data": "- ساحة رياض الصلح"
        },
        {
          "type": "text",
          "data": "- ساحة النجمة"
        },
        {
          "type": "text",
          "data": "- باب ادريس"
        },
        {
          "type": "text",
          "data": "والجادات والشوارع التالية:"
        },
        {
          "type": "text",
          "data": "- شارع الشام- بين ساحتي الدباس والشهداء"
        },
        {
          "type": "text",
          "data": "- شارع الامير بشير"
        },
        {
          "type": "text",
          "data": "- شارع البطريرك الحويك- لغاية جادة الافرنسيين"
        },
        {
          "type": "text",
          "data": "- شارع بشاره الخوري- لغاية مفرق شارع داود عمون"
        },
        {
          "type": "text",
          "data": "- جادة الفرنسيين"
        },
        {
          "type": "text",
          "data": "- شارع صور- من مفرق شارع رفيق سلوم الى مفرق شارع اغريبا"
        },
        {
          "type": "text",
          "data": "- شارع غورو- من ساحة الشهداء لغاية مفرق شارع سعيد عقل"
        },
        {
          "type": "text",
          "data": "- شارع عريس  وكنفاني الذي يربط ساحة الدباس بشارع غورو"
        },
        {
          "type": "text",
          "data": "- شارع الحمراء- من شارع روما لغاية شارع السادات"
        },
        {
          "type": "text",
          "data": "- السوق التجارية(ستاركو)"
        },
        {
          "type": "text",
          "data": "2)المنطقة الاولى وهي تشمل الجادات والشوارع التالية:"
        },
        {
          "type": "text",
          "data": "- شارع الشام لغاية شارع اسحق ابن حنين"
        },
        {
          "type": "text",
          "data": "- شارع البسطة- لغاية شارع صالح بن يحيى"
        },
        {
          "type": "text",
          "data": "- شارع جورج بيكو وشارع برتوى- لغاية شارع فينيقيا"
        },
        {
          "type": "text",
          "data": "- شارع صور"
        },
        {
          "type": "text",
          "data": "- شارع ميناء الحصن"
        },
        {
          "type": "text",
          "data": "- شارع دار المريسه"
        },
        {
          "type": "text",
          "data": "- شارع باريس"
        },
        {
          "type": "text",
          "data": "- شارع شوران"
        },
        {
          "type": "text",
          "data": "3) جميع الحوانيت الواقعة داخل المنطقة المحددة بالشوارع"
        },
        {
          "type": "text",
          "data": "التالية:"
        },
        {
          "type": "text",
          "data": "- شارع غورو- من اول ساحة الشهداء"
        },
        {
          "type": "text",
          "data": "- شارع جورج حداد"
        },
        {
          "type": "text",
          "data": "- شارع المرفأ"
        },
        {
          "type": "text",
          "data": "- البحر لغاية شارع بوردو"
        },
        {
          "type": "text",
          "data": "- شارع بوردو"
        },
        {
          "type": "text",
          "data": "- شارع جورج بيكو"
        },
        {
          "type": "text",
          "data": "- شارع الكبوشيين"
        },
        {
          "type": "text",
          "data": "- شارع البسطة لغاية شارع الامير امين"
        },
        {
          "type": "text",
          "data": "- شارع الامير امين"
        },
        {
          "type": "text",
          "data": "- شارع الام جيلاس"
        },
        {
          "type": "text",
          "data": "- شارع المخلصية والشوارع الممتدة منه لغاية شارع بشاره"
        },
        {
          "type": "text",
          "data": "الخوري"
        },
        {
          "type": "text",
          "data": "- شارع سعيد عقل- من شارع المخلصية لغاية شارع غورو, وكذلك جميع الحوانيت الموجودة في هذه الشوارع او اقسامها."
        },
        {
          "type": "text",
          "data": "يستثنى من المنطقة الاولى جميع الساحات والشوارع واقسامها المصنفة في المنقطة الممتازة."
        },
        {
          "type": "text",
          "data": "المنطقة الثانية وهي تشمل باقي مدينة بيروت ."
        }
      ]
    },
    {
      "number": "1",
      "content": [
        {
          "type": "text",
          "data": "مادة 2:\r\nتقسم مدينة  طرابلس  الى منطقتين هما:\r\nالمنطقة الاولى وهي تشمل الشوارع والساحات  التالية:\r\n- شارع باب  التبانة\r\n- سوق القمح\r\n- سوق خانم\r\n- باب  الحديد\r\n- سوق الخضرا الجديد\r\n-سوق المسلخ\r\n- سوق السويقه\r\n- سوق الحلاج\r\n- سوق البازركان\r\n- سوق الدباغة\r\n- خان الاصفر\r\n- سوق الصاغة\r\n-سوق قهوة الحتي\r\n- سوق البلدية القديمة\r\n- سوق الراهبات\r\n- سوق الامير خالد\r\n-سوق باب  الرامي\r\n- سوق التل\r\n- سوق اليزبك\r\n-سوق عزمي\r\n- سوق الحديد\r\n- سوق الزاهرية\r\n- سوق المسيحية\r\n- سوق العطارين\r\n- سوق بوابة الحدادين\r\n- سوق سويقة النوري\r\n- سوق قهوة الطرطوسي\r\n- سوق النجمه\r\n- سوق العجم\r\n- سوق عز الدين\r\n- سوق محمد كرامي\r\nالمنطقة الثانية وهي تشمل باقي اقسام واحياء المدينة.\r\nكازينو معاملتين- يعتبر من المنطقة الممتازة (بيروت )"
        }
      ]
    },
    {
      "number": "2",
      "content": [
        {
          "type": "text",
          "data": "مادة 4:\nالرسوم السنوية\nتستوفى عن كل رخصة بيع جديد رسوم سنوية \"عادية\" في العشر\nسنوات  الاولى اعتبارا من تاريخ اعطاء الرخصة, ورسوم سنوية\nمخفضة بعد انقضاء العشر سنوات  المذكورة.\nتحدد الرسوم السنوية كما يلي:\nقيمة الرسم   قيمة الرسم\nالسنوي العادي  السنوي المخفض\nالمتوجب  دفعه  المتوجب  دفعه\nطوال السنوات   اعتبارا من اول\nالعشر الاولى   السنة الحادية\nالامكنة والمناطق            اعتبارا من     عشرة التالية\nتاريخ اعطاء    لاعطاء الرخصة\nالرخصة\nل ل             ل ل\n-------------------------------------------------------\n-في بيروت -   المنطقة\nالممتازة    550             90\nفي بيروت - المنطقة الاولى      450             90\nفي بيروت - المنطقة الثانية     325             60\nفي طرابلس - المنطقة الاولى     200             60\nفي طرابلس - المنطقة الثانية    125             45\n----------------------------\nفي الامكنة التي يفوق عدد   سكانها 15000 نسمة\n----------------\nالمنطقة الاولى                 100             50\nالمنطقة الثانية                60              35\nسكانها بين 5001 و15000 نسمة وفي عاليه وبحمدون. ----------------المنطقة\nالاولى           75                 35 المنطقة الثانية          40\n20 ---------------في الامكنة التي يتراوح عدد سكانها بين 2501\nو5000 نسمة وفي صوفر وضهور الشوير وبرمانا وبيت  مري وشتورا وشكا والهرى\n------------------------منطقة وحيدة             40                  20\nفي الامكنة التي يترواح عدد سكانها بين 1001 و2500 نسمة وفي ريفون منقطة\nوحيدة             25                  15 -----------في الامكنة التي لا\nيزيد عدد سكانها عن 1000 نسمة                         مجانا\n--------------------\n--------------------------------\n-تعتبر رخصة البيع معطاة في اول كانون الثاني\nاو اول تموز حسبما تكون اعطيت  خلال النصف  الاول او النصف  الثاني من\nالسنة.\nويستوفى عن الرخص  المعطاة خلال نصف  السنة الثاني رسم يساوي نصف  قيمة\nالرسم السنوي.\nاذا اعطيت  الرخصة خلال نصف  السنة الثاني, فان نصف  الرسم\nالسنوي\nالعادي الذي لم يكن قد استوفى في السنة الاولى لاعطاء الرخصة, يستوفى عن\nالنصف  الاول من السنة الحادية عشرة من التقويم الغريغوري وفي هذه الحال\nيستوفى عن النصف  الثاني من السنة الحادية عشرة بالاضافة الى نصف  الرسم\nالسنوي العادي السابق ذكره, نصف  الرسم السنوي المخفض .\nان الباعة الحاصلين على رخصة بيع قبل تطبيق احكام هذه المادة يعتبرون كأنهم سددوا جميع الرسوم السنوية العادية ولا يؤدون الا الرسم السنوي المخفض ."
        },
        {
          "type": "text",
          "data": "قيمة الرسم السنوي   قيمة الرسم السنوي\nالعادي المتوجب      المخفض  المتوجب\nالامكنة والمناطق     دفعه طوال السنوات   دفعه اعتبارا من\nالعشر الاولى        اول السنة الحادية\nاعتبارا من تاريخ    عشرة التالية\nاعطاء الرخصة        لاعطاء الرخصة\nل ل                 ل ل\n-------------------------------------------------------\n-في الامكنة التي يتراوح\nالمادة 3 من المرسوم 2490 ت 17/2/94 خلافا للمادة الرابعة\nمن القرار 2401 تاريخ 26/7/1960 تفرض الرسوم السنوية بصورة\nمستمرة ودون اي تخفيض .تعدل الرسوم السنوية التي تستوفى\nعن رخص البيع بالمفرق بموجب المادة الرابعة من القرار رقم\n2401/1 تاريخ 26/7/1960 بحيث تضاعف مئة وخمسين مرة اكثر\nقيم الرسوم المذكورة."
        }
      ]
    },
    {
      "number": "3  مادة ملغاة  (الغيت بموجب قرار 2490 / 1994)",
      "content": [
        {
          "type": "text",
          "data": "حوانيت بعدة ابواب ."
        },
        {
          "type": "text",
          "data": "عندما يكون للحانوت عدة ابواب او شبابيك بيع تطل على مناطق من درجات مختلفة, يعتبر الحانوت واقعا في المنطقة الاعلى درجة بين المناطق التي تطل عليها ابوابه وشبابيكه هذه."
        }
      ]
    },
    {
      "number": "4",
      "content": [
        {
          "type": "text",
          "data": "نقل الحوانيت"
        },
        {
          "type": "text",
          "data": "يجوز لحامل رخصة البيع ان يطلب نقل حانوته من مكان الى اخر في منطقة من الدرجة نفسها او من درجة ادنى منها وذلك مع مراعاة شروط المسافة المفروضة لاعطاء رخصة جديدة في المنطقة المراد النقل اليها."
        },
        {
          "type": "text",
          "data": "لا يجوز نقل استثمار رخصة بيع الا الى حانوت او مؤسسة يملكها مواطن لبناني."
        },
        {
          "type": "text",
          "data": "في حال نقل الحانوت الى منطقة من درجة ادنى من درجة المنطقة التي كان فيها, لا يعاد للبائع فرق الرسم السنوي بين هاتين المنطقتين يمكن الترخيص بنقل حانوت من منطقة ذات  درجة معينة الى منطقة ذات درجة اعلى وذلك بالشروط التالية:"
        },
        {
          "type": "text",
          "data": "1- توفر شرط المسافة."
        },
        {
          "type": "text",
          "data": "2- يعتبر البائع الذي يكون قد استحصل على رخصة بيع قبل تطبيق هذا القرار كأنه سدد خلال عشر سنوات الرسم السنوي \"العادي\" المنصوص عليه في المادة الخامسة من هذا القرار والمفروض على درجة حانوته."
        },
        {
          "type": "text",
          "data": "3- على كل بائع يطلب نقل حانوته ان يسدد, دفعه واحدة, وعند الترخيص له بالنقل, الفرق بين مجمل الرسوم السنوية العادية التي يكون قد دفعها او المتوجب عليه دفعها, وبين الرسوم التي كان عليه ان يدفعها وفقا للتعرفة المعمول بها, فيما اذا كانت الرخصة معطاة بالاساس في الدرجة التي يرغب نقل حانوته اليها."
        },
        {
          "type": "text",
          "data": "4- على البائع ان يدفع, اعتبارا من تاريخ نقله, الرسم السنوي العادي او المخفض المفروض على الدرجة التي يكون قد نقل اليها حسب تاريخ منحه رخصة البيع."
        }
      ]
    },
    {
      "number": "5",
      "content": [
        {
          "type": "text",
          "data": "قياس المسافات بين الحوانيت: يجري قياس المسافات بين الحوانيت الجديدة والحوانيت المجاورة من منتصف باب الى منتصف باب."
        },
        {
          "type": "text",
          "data": "اذا كانت الابواب التي ينبغي قياس المسافات بينها واقعة على جانبي الشارع فتعتمد الطريقة التالية:"
        },
        {
          "type": "text",
          "data": "توضع خطوط عمودية من منتصف كل من هذه الابواب الى الجهة الثانية من الشارع وتقاس هذه الخطوط ثم يجمع نصفاها ويضاف الى مجمل المسافة التي تفصل وسطيها."
        },
        {
          "type": "text",
          "data": "اذا كان للحانوت عدة ابواب او شبابيك واقعة في مناطق من درجة واحدة يؤخذ بعين الاعتبار لقياس المسافة الباب الاقرب الى الحانوت المجاور."
        },
        {
          "type": "text",
          "data": "اذا كان للحانوت ابواب واقعة في مناطق من درجات مختلفة يعتبر كأنه واقع في منطقة من الدرجة الاعلى."
        },
        {
          "type": "text",
          "data": "تعتبر اجزاء المتر التي تفوق الخمسين سنتيمترا مترا كاملا."
        },
        {
          "type": "text",
          "data": "يمكن لادارة الحصر ان تتساهل لغاية المترين في حالة نقل الحانوت وفي حال اعطاء رخص جديدة."
        },
        {
          "type": "text",
          "data": "اذا كان الحانوت المقترح موجودا على زاوية مشطوبة وليس له الا مدخل واقع على هذه الزاوية, فيجب اعتباره موجودا في الشارع ذاته بالنسبة الى اقرب الحوانيت الموجودة"
        },
        {
          "type": "text",
          "data": "في الشوارع التي تشكل هذه الزاوية المشطوبة والتي تكملها على خط مستقيم."
        },
        {
          "type": "text",
          "data": "واذا كان الحانوت المقترح واقعا في احد طوابق بناية ما, فيجب اعتبار البناية واقعة في المنطقة التي يوجد فيها مدخلها, وقياس المسافات على الصورة المبينة سابقا مع اضافة مسافة المدخل واضافة 12 مترا لكل طابق."
        },
        {
          "type": "text",
          "data": "ويعتبر هذا الحانوت كأنه في شارع آخر بالنسبة الى الحوانيت الموجودة في الشارع وبالنسبة الى الحوانيت الموجودة في الطوابق الاخرى من البناية الا انه يعتبر في الشارع ذاته بالنسبة الى الحوانيت الموجودة في الطابق ذاته."
        },
        {
          "type": "text",
          "data": "اذا كان للبناية عدة مداخل من شوارع مختلفة الدرجات, فيجب اعتبار الحوانيت الموجودة فيها واقعة في الشارع ذي الدرجة الاعلى."
        }
      ]
    },
    {
      "number": "6",
      "content": [
        {
          "type": "text",
          "data": "تلغى جميع القرارات الوزارية العائدة لتنظيم منح رخص بيع التبغ والتنباك واخصها القرارات رقم 1084 تاريخ 12/10/1951 ورقم 1233 تاريخ 29/12/1951 ورقم 1234 تاريخ 29/12/1951 ورقم 822 تاريخ 15 كانون الاول سنة 1954"
        }
      ]
    },
    {
      "number": "7",
      "content": [
        {
          "type": "text",
          "data": "ينشر هذا القرار في الجريدة الرسمية ويطبق ابتداء من اول تموز سنة 1960"
        }
      ]
    }
  ],
  "signature": "بيروت  في 26 تموز سنة 1960\nوزير المالية\nالامضاء: امين بيهم"
}