{
  "url": "http://77.42.251.205/LawView.aspx?opt=view&LawID=195715",
  "title": "تصديق محاضر لجنة وخريطة تتعلق بتعيين حدود املاك عمومية\r\nمكونة من مياه نبع فرح ونبع القطين والعيون الصغيرة المجاورة\r\nلها والكائنة بخراج عرامون كسروان",
  "metadata": {
    "type": "تعريف النص: مرسوم",
    "number": "13689",
    "date": " 23/11/1948",
    "oj_number": "48",
    "oj_publish_date": "01/12/1948",
    "oj_page": "918"
  },
  "preamble": "",
  "articles": [
    {
      "number": "2 \r\nمادة 2:\r\nيبلغ هذا المرسوم وينشر حيث  تدعو الحاجة.",
      "content": [
        {
          "type": "text",
          "data": "مادة 1:\r\nصدقت  محاضر اللجنة المذكورة المؤرخة في 28 شباط سنة 1948\r\nو26 آب  سنة 1948 والخريطة الملحقة بهما (1) والمعلم عليها\r\nبالحبر الاحمر والتي تعين حدود الاملاك العمومية المكونة من\r\nمياه نبع فرح ونبع القطين والعيون الصغيرة المجاورة لهما\r\nوالكائنة بخراج عرامون ( قضاء كسروان)."
        }
      ]
    },
    {
      "number": "1",
      "content": [
        {
          "type": "text",
          "data": "مادة 2:\r\nيبلغ هذا المرسوم وينشر حيث  تدعو الحاجة."
        }
      ]
    }
  ],
  "signature": "بيروت  في 23 تشرين الثاني سنة 1948\nالامضاء: بشارة خليل الخوري\nصدر عن رئيس  الجمهورية\nرئيس  مجلس  الوزراء بالوكالة     وزير الاشغال العامة\nالامضاء: جبرائيل المر       الامضاء: احمد الاسعد"
}