{
  "url": "http://77.42.251.205/LawView.aspx?opt=view&LawID=205155",
  "title": "بتحويل انشاءات  امتيازات  كهرباء لبنان الشمالي الى\r\nمصلحة كهرباء لبنان",
  "metadata": {
    "type": "تعريف النص: مرسوم",
    "number": "3666",
    "date": " 10/02/1987",
    "oj_number": "8",
    "oj_publish_date": "19/02/1987",
    "oj_page": "70"
  },
  "preamble": "ان رئيس  الجمهورية\nبناء على الدستور\nبناء على القانون الموضوع موضع التنفيذ بموجب  المرسوم\nرقم 16878 تاريخ 10/7/1964 (لا سيما المادة الثالثة منه),\nبناء على قرار مجلس  الوزراء رقم 21 تاريخ 22/8/1985 وقراره\nرقم 12 تاريخ 11/4/1986,\nبناء على اقتراح وزيري المالية والموارد المائية والكهربائية,\nيرسم ما يأتي:",
  "articles": [
    {
      "number": "3  ينشر هذا المرسوم ويبلغ حيث تدعو الحاجة.",
      "content": [
        {
          "type": "text",
          "data": "تحول الى مصلحة كهرباء لبنان جميع الانشاءات والتجهيزات والمعدات وموجودات المخزن العائدة لشركة كهرباء لبنان الشمالي المستردة بموجب قرار مجلس الوزراء رقم 21 تاريخ 22/8/1985 بما في ذلك الاملاك."
        }
      ]
    },
    {
      "number": "1",
      "content": [
        {
          "type": "text",
          "data": "تحدد هذه الانشاءات والتجهيزات والمعدات وموجودات المخزن والاملاك وقيمتها جميعا بموجب المخالصة الجاري اعدادها بين الدولة واصحاب الشركة."
        }
      ]
    },
    {
      "number": "2",
      "content": [
        {
          "type": "text",
          "data": "ينشر هذا المرسوم ويبلغ حيث تدعو الحاجة."
        }
      ]
    }
  ],
  "signature": "بعبدا في 10 شباط 1987\nالامضاء: امين الجميل\nصدر عن رئيس  الجمهوية\nرئيس  مجلس  الوزراء\nالامضاء: رشيد كرامي\nوزير الموارد المائية والكهربائية\nالامضاء: نبيه بري\nوزير المالية\nالامضاء: كميل شمعون"
}