{
  "url": "http://77.42.251.205/RulingView.aspx?opt&RulID=65604",
  "title": ":: الجامعة اللبنانية - مركز الدراسات القانونية ::الأحكام ::  رؤية الحكمتمييز جزائي حكم رقم : 147 /1970",
  "card_info": {
    "court": "تمييز جزائي",
    "number": "147",
    "year": "1970",
    "session_date": "19/05/1970",
    "chief": "منير محمصاني",
    "members": "/حريز//بولس\r\n/"
  },
  "ruling_text": "*  مفعول صدور  قرار الهيئة الاتهامية لجهة العيوب  القانونية السابقة له كعدم تنظيم  النيابة العامة تقريرا ضمن المهلة القانونية  *\nلجهة مخالفة احكام المواد  250 , 251 ,252 من الاصول الجزائية:  بما ان ادعاء طالب  النقض  انه حصلت  مخالفة لاحكام المواد 250 ,251 ,  252 من قانون اصول المحاكمات  الجزائية بشأن عدم تنظيم المدعي العام  تقريرا في مهلة خمسة ايام من استلام الاوراق المرسلة اليه وشأن تعطيل  احكام المادتين 251 , 252 بسبب  عدم تنظيم تقرير النيابة العامة, لا  يمكن في حال صحته ان يعتبر سببا للنقض , بعد صدور قرار الهيئة الاتهامية  الذي يمحو كل الاخطاء التي سبقته, والذي كان بامكان طالب  النقض  ان  يستدعي تصحيحها تمييزا, فلم يفعل, وبما انه يقتضي رد هذا السبب .\n*  في حق  محكمة الجنايات  تقدير الوقائع وتطبيق المواد القانونية ومدى رقابة  محكمة التمييز  *\nبما ان المحكمة بما لها من السلطان في تقدير الوقائع  والادلة ان حق التحقيق الجاري اعتبرت  ان فصل التهم ينطبق على المادة  555 ق . ع . وليس  على المادتين 54 و 201 من نفس  القانون   وبما انه ليس  لمحكمة التمييز ان تفرض  رقابتها على قناعة المحكمة  وتقديرها لوقائع وظروف  الدعوى  وبما انه يقتضي رد هذا السبب  ايضا"
}