{
  "url": "http://77.42.251.205/LawView.aspx?opt=view&LawID=243914",
  "title": "تنظيم ادارة الاحصاء المركزي وتحديد ملاكها والشروط الخاصة للتعيين في وظائف هذا الملاك وسلسلة رتبها ورواتبها وتحديد التعويضات وشروط التصنيف",
  "metadata": {
    "type": "تعريف النص: مرسوم",
    "number": "2728",
    "date": " 28/02/1980",
    "oj_number": "13",
    "oj_publish_date": "27/03/1980",
    "oj_page": "229-244"
  },
  "preamble": "ان رئيس الجمهورية,\nبناء على الدستور,\nبناء على مشروع القانون الموضوع موضع التنفيذ بالمرسوم رقم 1793 تاريخ 22/2/1979 (انشاء ادارة الاحصاء المركزي) ولا سيما المادة الرابعة منه,\nوبعد استشارة مجلس شورى الدولة,\nوبعد موافقة هيئة مجلس الخدمة المدنية بقرارها رقم 704 تاريخ 11/12/1979,\nبناء على اقتراح رئيس مجلس الوزراء,\nوبعد موافقة مجلس الوزراء بتاريخ 29/12/1979,\nيرسم ما يأتي:",
  "articles": [
    {
      "number": "59  ينشر هذا المرسوم ويبلغ حيث تدعو الحاجة ويعمل به فور نشره في الجريدة الرسمية.",
      "content": [
        {
          "type": "text",
          "data": "تتألف ادارة الاحصاء المركزي من:"
        },
        {
          "type": "text",
          "data": "- مصلحة الديوان."
        },
        {
          "type": "text",
          "data": "- مصحلة احصاءات قطع الانتاج."
        },
        {
          "type": "text",
          "data": "- مصلحة احصاءات القطاع المنزلي والاجتماعي."
        },
        {
          "type": "text",
          "data": "- مصلحة العمليات الميدانية والاحصاءات الاقليمية."
        },
        {
          "type": "text",
          "data": "- مصلحة المركز الآلي."
        },
        {
          "type": "text",
          "data": "- مصلحة التنسيق والمحاسبة الوطنية."
        },
        {
          "type": "text",
          "data": "- مصلحة التوثيق والنشر والطباعة."
        }
      ]
    },
    {
      "number": "1",
      "content": [
        {
          "type": "text",
          "data": "تتولى مصلحة الديوان المهام والصلاحيات التي تنيطها القوانين والانظمة بالديوان في الادارات العامة."
        }
      ]
    },
    {
      "number": "2",
      "content": [
        {
          "type": "text",
          "data": "تتألف مصلحة الديوان من:"
        },
        {
          "type": "text",
          "data": "- الدائرة الادارية"
        },
        {
          "type": "text",
          "data": "- دائرة المحاسبة"
        },
        {
          "type": "text",
          "data": "- دائرة التجهيزات واللوازم"
        }
      ]
    },
    {
      "number": "3",
      "content": [
        {
          "type": "text",
          "data": "تتولى الدائرة الادارية:"
        },
        {
          "type": "text",
          "data": "- تأمين اعمال البريد والمحفوظات والاستكتاب وتوزيع المخابرات والمواصلات والنقل والخدمة الداخلية وسائر الخدمات العامة للادارة."
        },
        {
          "type": "text",
          "data": "- الشؤون الذاتية للموظفين والمتعاقدين والاجراء وسائر العاملين في ادارة الاحصاء المركزي."
        }
      ]
    },
    {
      "number": "4",
      "content": [
        {
          "type": "text",
          "data": "تتولى دائرة المحاسبة:"
        },
        {
          "type": "text",
          "data": "- اعداد مشروع الموازنة والقيام بالمعاملات التي لها علاقة بتنفيذ الموازنة ومسك حساباتها."
        }
      ]
    },
    {
      "number": "5",
      "content": [
        {
          "type": "text",
          "data": "تتولى دائرة التجهيزات واللوازم:"
        },
        {
          "type": "text",
          "data": "- تأمين التجهيزات واللوازم الفنية والادارية اللازمة لادارة الاحصاء المركزي ووضع دفاتر الشروط الفنية العائدة لها ومسك محاسبة هذه التجهيزات واللوازم."
        },
        {
          "type": "text",
          "data": "- صيانة المباني والتجهيزات ."
        }
      ]
    },
    {
      "number": "6",
      "content": [
        {
          "type": "text",
          "data": "تتولى مصلحة احصاءات قطاع الانتاج:"
        },
        {
          "type": "text",
          "data": "- وضع الاحصاءات المتعلقة بالثروات الطبيعية ونشاط القطاعات الاقتصادية: الزراعة والصناعة والطاقة والبناء والنقل والمواصلات والسياحة والخدمات الاخرى والاسعار والتجارة الداخلية والتجارة الخارجية وذلك بالتعاون مع الادارات المختصة."
        },
        {
          "type": "text",
          "data": "- تنظيم مبطقة لمؤسسات الانتاج وتيويمها والتنسيق بين المبطقات المماثلة الموجودة لدى الادارات العامة والبلديات والمؤسسات العامة الاخرى."
        },
        {
          "type": "text",
          "data": "- الاشراف الفني على وحدات الاحصاء في الوزارات والادارات العامة الاخرى التي تعنى بشؤون مؤسسات الانتاج كوزارة الزراعة ووزارة الصناعة والنفط ووزارة الاقتصاد والتجارة ووزارة الاشغال العامة والنقل ووزارة الموارد المائية والكهربائية ووزارة البريد والبرق والهاتف ووزارة السياحة الخ.... والعمل على تحسين الاساليب المستعملة في وضع الاحصاءات الناتجة عن اعمالها وفي استخراج المعلومات الاحصائية المتوفرة لديها. - تحضير التحقيقات الاحصائية الدورية لدى مؤسسات الانتاج واستخلاص نتائجها وتحليلها."
        },
        {
          "type": "text",
          "data": "- وضع الحسابات الاولية لقطاع الانتاج في اطار المحاسبة الوطنية العامة."
        }
      ]
    },
    {
      "number": "7",
      "content": [
        {
          "type": "text",
          "data": "تتألف مصلحة احصاءات قطاع الانتاج من:"
        },
        {
          "type": "text",
          "data": "- دائرة مبطقة مؤسسات الانتاج."
        },
        {
          "type": "text",
          "data": "- دائرة احصاءات التجارة الخارجية."
        },
        {
          "type": "text",
          "data": "- دائرة الاسعار واحصاءات التجارة الداخلية."
        },
        {
          "type": "text",
          "data": "- ومن فرق عمل تتألف بقرار من المدير العام بناء على اقتراح رئيس المصلحة تتولى القيام بالاحصاءات والدراسات وفاقا لبرامج عمل سنوية او معدة لعدة سنوات ."
        }
      ]
    },
    {
      "number": "8",
      "content": [
        {
          "type": "text",
          "data": "تتولى دائرة مبطقة مؤسسات الانتاج:"
        },
        {
          "type": "text",
          "data": "- تنظيم مبطقة مؤسسات الانتاج حسب مواصفات نشاطها الاقتصادي وموقعها الجغرافي وعدد العاملين فيها."
        },
        {
          "type": "text",
          "data": "- اعطاء رقم تسلسلي خاص لكل مؤسسة والسعي لتوحيد هذه الارقام مع مختلف الادارات والمؤسسات المختصة."
        },
        {
          "type": "text",
          "data": "- وضع احصاءات دورية عن حركة المبطقة."
        }
      ]
    },
    {
      "number": "9",
      "content": [
        {
          "type": "text",
          "data": "تتولى دائرة احصاءات التجارة الخارجية."
        },
        {
          "type": "text",
          "data": "- وضع احصاءات التجارة الخارجية وذلك بالتعاون مع الادارة العامة للجمارك."
        },
        {
          "type": "text",
          "data": "- القيام بالدراسات المتعلقة بالتجارة الخارجية بما فيها دراسة اسعار السلع المستوردة والمصدرة."
        },
        {
          "type": "text",
          "data": "- تحضير الجداول الاولية العائدة للمبادلات الخارجية في نطاق المحاسبة الوطنية."
        }
      ]
    },
    {
      "number": "10",
      "content": [
        {
          "type": "text",
          "data": "تتولى دائرة الاسعار واحصاءات التجار الداخلية:"
        },
        {
          "type": "text",
          "data": "- جميع اسعار الجملة لمختلف السلع ومراقبة تطور هذه الاسعار في مختلف مراحل التسويق"
        },
        {
          "type": "text",
          "data": "- جمع اسعار المفرق للمواد الغذائية والالبسة والادوات المنزلية واسعار الخدمات في مختلف القطاعات بصورة دورية منتظمة."
        },
        {
          "type": "text",
          "data": "- احتساب الارقام القياسية لاسعار الجملة والمفرق لكل مجموعة من السلع حسب استعمالها والارقام القياسية لغلاء المعيشة."
        },
        {
          "type": "text",
          "data": "- تقدير ودرس الهوامش التجارية الداخلية في اطار المحاسبة الوطنية."
        }
      ]
    },
    {
      "number": "11",
      "content": [
        {
          "type": "text",
          "data": "نتولى مصلحة احصاءات القطاع المنزلي والاجتماعي:"
        },
        {
          "type": "text",
          "data": "- وضع الاحصاءات المتعلقة بالاسكان والصحة والتعليم والقوى العامة والدخل واستهلاك الاسر ونشاط المؤسسات ذات الطابع الثقافي والاجتماعي وذلك بالتعاون مع الادارات المختصة."
        },
        {
          "type": "text",
          "data": "- الاشراف الفني على وحدات الاحصاء في الوزارات والادارات العامة والمؤسسات العامة الاخرى التي تهتم بالشؤون الاجتماعية كوزارة الاسكان والتعاونيات ووزارة العدل ووزارة التربية الوطنية والفنون الجميلة ووزارة الصحة العامة ووزارة العمل والشؤون الاجتماعية والصندوق الوطني للضمان الاجتماعي الخ... والعمل على تحسين الاساليب المستعملة في وضع الاحصاءات الناتجة عن اعمالها واستخراج المعلومات الاحصائية المتوفرة لديها."
        },
        {
          "type": "text",
          "data": "- تحضير التحقيقات الاحصائية الدورية لدى الاسر والمؤسسات الاجتماعية والثقافية واستخلاص نتائجها وتحليلها."
        },
        {
          "type": "text",
          "data": "- تحضير الحسابات الاولية للقطاع المنزلي والمؤسسات الاجتماعية في اطار المحاسبة الوطنية العامة."
        }
      ]
    },
    {
      "number": "12",
      "content": [
        {
          "type": "text",
          "data": "تتألف مصلحة احصاءات القطاع المنزلي والاجتماعي من:"
        },
        {
          "type": "text",
          "data": "- دائرة احصاءات الاسكان."
        },
        {
          "type": "text",
          "data": "- دائرة احصاءات قوى اليد العاملة."
        },
        {
          "type": "text",
          "data": "- ومن فرق عمل تتألف بقرار من المدير العام بناء على اقتراح رئيس المصلحة تتولى القيام بالاحصاءات وبالدراسات ضمن صلاحيات المصلحة ووفاقا لبرامج عمل سنوية او معدة لعدة سنوات ."
        }
      ]
    },
    {
      "number": "13",
      "content": [
        {
          "type": "text",
          "data": "تتولى دائرة احصاءات الاسكان:"
        },
        {
          "type": "text",
          "data": "- تحضير التحقيقات الاحصائية الدورية العائدة للمساكن استخلاص نتائجها."
        },
        {
          "type": "text",
          "data": "- تنظيم بطاقة خاصة لكل مبنى حسب الموقع الجغرافي ومواصفات البناء والتجهيزات."
        },
        {
          "type": "text",
          "data": "- وضع احصاءات دورية عن المساكن وعن الايجارات وذلك بالتعاون مع الجهات المختصة."
        }
      ]
    },
    {
      "number": "14",
      "content": [
        {
          "type": "text",
          "data": "تتولى دائرة احصاءات قوى اليد العاملة:"
        },
        {
          "type": "text",
          "data": "- تحضير التحقيقات الاحصائية لدى الاسر لمعرفة نسب الاستخدام والبطالة وتوزيع اليد العاملة على مختلف المهن والقطاعات وتحليل نتائجها."
        },
        {
          "type": "text",
          "data": "- وضع احصاءات دورية عن الاستخدام والبطالة بالتعاون مع الادارات المختصة."
        }
      ]
    },
    {
      "number": "15",
      "content": [
        {
          "type": "text",
          "data": "تتولى مصلحة العمليات الميدانية والاحصاءات الاقليمية:"
        },
        {
          "type": "text",
          "data": "- الاعمال الميدانية (جميع المعلومات من الادارات العامة ومن المؤسسات العامة والخاصة التي تطلبها مختلف الوحدات في ادارة الاحصاء المركزي وجميع الاعمال الميدانية في المناطق)."
        },
        {
          "type": "text",
          "data": "- تنفيذ التحقيقات الاحصائية في الميدان."
        },
        {
          "type": "text",
          "data": "- وضع الاحصاءات الاقليمية بالتعاون مع الهيئات الاقليمية."
        }
      ]
    },
    {
      "number": "16",
      "content": [
        {
          "type": "text",
          "data": "تتألف مصلحة العمليات الميدانية والاحصاءات الاقليمية من:"
        },
        {
          "type": "text",
          "data": "- مكتب اقليمي في كل محافظة."
        },
        {
          "type": "text",
          "data": "- مكتب بيروت ."
        }
      ]
    },
    {
      "number": "17",
      "content": [
        {
          "type": "text",
          "data": "تتولى المكاتب الاقليمية في المحافظات :"
        },
        {
          "type": "text",
          "data": "- جمع المعلومات التي تطلبها مختلف المصالح في ادارة الاحصاء المركزي من الادارات العامة والمؤسسات الرسمية والخاصة."
        },
        {
          "type": "text",
          "data": "- تنفيذ التحقيقات الاحصائية في نطاق المحافظة."
        },
        {
          "type": "text",
          "data": "- وضع الاحصاءات الاقليمية وذلك بالتعاون مع الهيئات المحلية في المحافظة."
        }
      ]
    },
    {
      "number": "18",
      "content": [
        {
          "type": "text",
          "data": "يتولى مكتب بيروت :"
        },
        {
          "type": "text",
          "data": "تجميع وتركيز كل الاحصاءات التي ترد من المكاتب الاقليمية الاخرى بالاضافة الى المهام الواردة في المادة السابقة وبالنسبة لمدينة بيروت ."
        }
      ]
    },
    {
      "number": "19",
      "content": [
        {
          "type": "text",
          "data": "تتولى مصلحة المركز الآلي:"
        },
        {
          "type": "text",
          "data": "- تنفيذ جميع اعمال معالجة المعلومات الاحصائية بواسطة الحاسب الالكتروني والالات والتجهيزات والمعدات الموضوعة بتصرفها واعطاء المشورة الفنية في تنظيم الاعمال الواجب معالجتها آليا وفي اعداد التصانيف والرموز."
        }
      ]
    },
    {
      "number": "20",
      "content": [
        {
          "type": "text",
          "data": "تتألف مصلحة المركز الآلي من:"
        },
        {
          "type": "text",
          "data": "- دائرة التحليل والبرمجة."
        },
        {
          "type": "text",
          "data": "- دائرة العمل الآلي."
        }
      ]
    },
    {
      "number": "21",
      "content": [
        {
          "type": "text",
          "data": "تتولى دائرة التحليل والبرمجة:"
        },
        {
          "type": "text",
          "data": "- وضع التصاميم العامة لمعالجة المعلومات الاحصائية."
        },
        {
          "type": "text",
          "data": "- تحديد نظام معالجة المعلومات الخاص بالحاسب الالكتروني وتنظيم مكتبة البرامج والبرامج المساعدة والبرامج المتعددة الاستعمال."
        },
        {
          "type": "text",
          "data": "- تحديد طريقة تنظيم التسجيلات على الذاكرات الممغنطة."
        },
        {
          "type": "text",
          "data": "- تحديد البرامج وكتابتها ورسوم التسجيلات والمطبوعات الواجب استخراجها وتعديل هذه البرامج عند الاقتضاء."
        },
        {
          "type": "text",
          "data": "- تدقيق الجداول المستخرجة عن الالات ."
        }
      ]
    },
    {
      "number": "22",
      "content": [
        {
          "type": "text",
          "data": "تتولى دائرة العمل الآلي:"
        },
        {
          "type": "text",
          "data": "- تنفيذ جيمع اعمال المعالجة الآلية للمعلومات الاحصائية بوسطة الحاسب الالكتروني والوحدات والالات والتجهيزات المساعدة او التحضيرية لهذه الاعمال."
        },
        {
          "type": "text",
          "data": "- وضع مخططات الاعمال الواجب معالجتها آليا والسهر على حسن تنفيذها."
        },
        {
          "type": "text",
          "data": "- حفظ الاستوانات والشرائط الممغنطة وترقيمها ووضع فهارس بمحتوياتها وبطريقة فرزها."
        },
        {
          "type": "text",
          "data": "- استلام وتسليم مختلف المستندات العائدة للوحدات التي تتم معالجة المعلومات لصالحها."
        }
      ]
    },
    {
      "number": "23",
      "content": [
        {
          "type": "text",
          "data": "تتألف دائرة العمل الآلي من:"
        },
        {
          "type": "text",
          "data": "- مشغل تحضير العمل الآلي والمحفوظات ."
        },
        {
          "type": "text",
          "data": "- مشغل تحويل المعلومات ."
        },
        {
          "type": "text",
          "data": "- مشغل الحاسب الالكتروني."
        }
      ]
    },
    {
      "number": "24",
      "content": [
        {
          "type": "text",
          "data": "تتولى مصلحة التنسيق والمحاسبة الوطنية:"
        },
        {
          "type": "text",
          "data": "- وضع الاطار العام والتصاميم للمحاسبة الوطنية."
        },
        {
          "type": "text",
          "data": "- تركيز الحاسبات الاولية التي تضعها الوحدات المختصة وقطع حساب موازنات الدولة والمؤسسات العامة والبلديات وحساب العملة المالية او الاحصاءات المالية التي يضعها مصرف لبنان والتنسيق بينها ووضع الحسابات النهائية."
        },
        {
          "type": "text",
          "data": "- وضع حسابات تقديرية مؤقتة والحسابات المرتقبة للنشاط الاقتصادي."
        },
        {
          "type": "text",
          "data": "- درس الاوضاع الاقتصادية والاجتماعية العامة ومراقبة تطورها."
        },
        {
          "type": "text",
          "data": "- توحيد الرموز والمصطلحات الاحصائية المستعملة في مختلف وحدات ادارة الاحصاء المركزي وفي الادارات العامة والمؤسسات العامة والبلديات وتعميمها."
        },
        {
          "type": "text",
          "data": "- القيام بالابحاث الضرورية لتحسين الاساليب الاحصائية وتعميمها."
        }
      ]
    },
    {
      "number": "25",
      "content": [
        {
          "type": "text",
          "data": "تتألف مصلحة التنسيق والمحاسبة الوطنية من فرق عمل تشكل بقرار من المدير العام بناء على اقتراح رئيس المصلحة وتتولى القيام بمهام المصلحة وفاقا لبرامج عمل سنوية او معدة لعدة سنوات ."
        }
      ]
    },
    {
      "number": "26",
      "content": [
        {
          "type": "text",
          "data": "تتولى مصلحة التوثيق والنشر والطباعة."
        },
        {
          "type": "text",
          "data": "- تركيز جميع المستندات المتعلقة بالنشاط الاقتصادي والاجتماعي للبلد والبلدان الاخرى والمجلات والابحاث العلمية في حقل الاحصاء والعلوم الاقتصادية والاجتماعية ووضع تصانيف لها."
        },
        {
          "type": "text",
          "data": "- تنظيم المكتبة وحفظها."
        },
        {
          "type": "text",
          "data": "- جميع اعمال الرسوم ووضع الخرائط الجغرافية."
        },
        {
          "type": "text",
          "data": "- طبع النماذج والاستمارات والمستندات الاخرى الخاصة بعمل ادارة الاحصاء المركزي."
        },
        {
          "type": "text",
          "data": "- اعداد النشرات الدورية وطبعها وتوزيعها."
        }
      ]
    },
    {
      "number": "27",
      "content": [
        {
          "type": "text",
          "data": "تتألف مصحلة التوثيق والنشر والطباعة من:"
        },
        {
          "type": "text",
          "data": "- دائرة التوثيق."
        },
        {
          "type": "text",
          "data": "- دائرة النشر."
        },
        {
          "type": "text",
          "data": "- دائرة الطباعة."
        }
      ]
    },
    {
      "number": "28",
      "content": [
        {
          "type": "text",
          "data": "تتولى دائرة التوثيق:"
        },
        {
          "type": "text",
          "data": "- تركيز جميع المستندات المتعلقة بالنشاط الاقتصادي والاجتماعي للبلاد والبلدان المجاورة والبلدان الاخرى والمجلات والابحاث العلمية في حقل الاحصاء والعلوم الاقتصادية والاجتماعية ووضع تصانيف لها."
        },
        {
          "type": "text",
          "data": "- تنظيم المكتبة والحفاظ عليها."
        },
        {
          "type": "text",
          "data": "- تزويد الموظفين الفنيين في ادارة الاحصاء المركزي والباحثين الاخرين خارج الادارة بالمنشورات والابحاث والمستندات المختلفة التي بحوزتها والتي يحتاجون اليها في اعمالهم وبحوثهم."
        },
        {
          "type": "text",
          "data": "- تزويد الجمهور بالمعلومات الاحصائية المنشورة او قيد النشر."
        }
      ]
    },
    {
      "number": "29",
      "content": [
        {
          "type": "text",
          "data": "تتولى دائرة النشر:"
        },
        {
          "type": "text",
          "data": "- تحضير النشرات الدورية واخراجها والاشراف على اصدارها."
        },
        {
          "type": "text",
          "data": "- توزيع النشرات التي تصدر عن ادارة الاحصاء المركزي."
        },
        {
          "type": "text",
          "data": "- اعمال رسم الرسوم البيانية والخرائط الجغرافية الاقتصادية والاجتماعية وجميع اعمال الرسم الاخرى."
        }
      ]
    },
    {
      "number": "30",
      "content": [
        {
          "type": "text",
          "data": "تتولى دائرة الطباعة:"
        },
        {
          "type": "text",
          "data": "- طبع النشرات الاحصائية والنماذج والمستندات الاخرى الضرورية لنشاط ادارة الاحصاء المركزي."
        }
      ]
    },
    {
      "number": "31",
      "content": [
        {
          "type": "text",
          "data": "تحدد الوظائف الفنية في ادارة الاحصاء المركزي كما يلي:"
        },
        {
          "type": "text",
          "data": "- وظيفة احصائي رئيس مصلحة:"
        },
        {
          "type": "text",
          "data": "يمارس الاحصائي رئيس مصلحة صلاحيات رئيس المصلحة على رأس احدى المصالح الفنية."
        },
        {
          "type": "text",
          "data": "- احصائي اول او احصائي:"
        },
        {
          "type": "text",
          "data": "يحدد الاحصائي اول او الاحصائي الاساليب ويضع التصاميم اللازمة للاعمال الاحصائية والدراسات ويراقب التنفيذ ويشرف عليه ويقوم بتحليل النتائج ويبين خلاصتها.وبشكل عام يدير تحت اشراف رئيس المصلحة المختصة الاعمال الاحصائية ويكون مسؤولا عن نتائجها."
        },
        {
          "type": "text",
          "data": "- احصائي مساعد اول او احصائي مساعد:"
        },
        {
          "type": "text",
          "data": "يعمل تحت اشراف الاحصائي اول او الاحصائي على وضع الاحصاءات العادية ويعاون الاحصائي في اعمال الدارسة, ويمكنه ايضا ان يراقب اعمال المحققين."
        },
        {
          "type": "text",
          "data": "- محقق اول:"
        },
        {
          "type": "text",
          "data": "يقوم تحت اشراف الاحصائي اول او الاحصائي بمراقبة اعمال المحققين في الميدان وتنفيذ التحقيقات التي تتطلب خبرة مميزة."
        },
        {
          "type": "text",
          "data": "- محقق:"
        },
        {
          "type": "text",
          "data": "يقوم المحقق بجمع المعلومات الناتجة عن المقابلات الشخصية او عن السجلات على نماذج معدة سابقا ويعيد تسجيلها بالرموز, وباعمال حسابية عادية, ويقوم بصورة عامة بجميع اعمال الاحصاء التي لا تتطلب مؤهلات تقنية عالية."
        },
        {
          "type": "text",
          "data": "- اختصاصي اول او اختصاصي في العلوم الاقتصادية او الاجتماعية او الجغرافية او الديموغرافية او ادارة الاعمال:"
        },
        {
          "type": "text",
          "data": "يقوم هؤلاء الاختصاصيون تحت اشراف الاخصائي رئيس مصلحة او الاحصائي (احصائي اول او احصائي), وكل في اختصاصه, بدراسة الوقائع الاقتصادية او الاجتماعية او الديموغرافية ويبينون خلاصتها, ويساهمون على الاخص في وضع الحسابات الاقتصادية وميزان المدفوعات وفي وضع الخرائط الجغرافية الاقتصادية والبشرية وفي تحليل حسابات المؤسسات الخاصة."
        },
        {
          "type": "text",
          "data": "- اختصاصي اول او اختصاصي في الرياضيات الاحصائية:"
        },
        {
          "type": "text",
          "data": "يقوم بتطبيق الاساليب الاحصائية الفنية على اختيار العينات واحتساب نسب الخطأ الناتجة من الواقع وتحليل الارتباط بين عدة متغيرات وبشكل عام مساعدة الاحصائي (احصائي اول واحصائي/في اعمال تحليلية تتطلب استعمال الاساليب الاحصائية الرياضية."
        },
        {
          "type": "text",
          "data": "- موثق اول او موثق:"
        },
        {
          "type": "text",
          "data": "يركز الاحصاءات والدروس وغيرها من المستندات التي تهم الحياة الاقتصادية والاجتماعية في لبنان والبلدان الاخرى ويصنفها بحسب الموضوع وبضع بطاقات وفهارس دالة تحتوي على خلاصة المستندات التي في حوزة الادارة العامة للاحصاء."
        },
        {
          "type": "text",
          "data": "- موثق مساعد:"
        },
        {
          "type": "text",
          "data": "يساعد الموثق (موثق اول او موثق) في اعمال التوثيق وفي ترتيب المكتبة والمحفوظات ."
        },
        {
          "type": "text",
          "data": "- محلل اول او محلل:"
        },
        {
          "type": "text",
          "data": "يضع التصاميم العامة لمعالجة المعلومات ويحدد البرامج الواجب كتابتها وطريقة تنظيم التسجيلات على الذاكرات الممغنطة ورسومها واللغات الواجب استعمالها في اعمال البرمجة. ويشارك في تحديد نظام معالجة المعلومات الخاص بالحاسب الالكتروني وفي التعديلات الواجب ادخالها عليه."
        }
      ]
    },
    {
      "number": "59  ينشر هذا المرسوم ويبلغ حيث تدعو الحاجة ويعمل به فور نشره في الجريدة الرسمية.",
      "content": [
        {
          "type": "text",
          "data": "بالاضافة الى الشروط العامة للتوظيف, يشترط في المرشحين للاشتراك في المباراة المؤهلة للتعيين في احدى الوظائف الفنية في ادارة الاحصاء المركزي ان يكونوا حائزين على الشهادات او الشروط المبينة امام كل وظيفة:"
        },
        {
          "type": "text",
          "data": "1- وظيفة احصائي:"
        },
        {
          "type": "text",
          "data": "- حيازة شهادة من معهد عال للاحصاء والعلوم الاقتصادية لا تقل الدراسة لنيلها عن ثلاث سنوات, ويعتبر معهدا عاليا للاحصاء والعلوم الاقتصادية المعهد الذي لا يقبل طلابا لديه الا من بين الاشخاص الحائزين على اجازة جامعية لا تقل الدراسة فيها عن ثلاث سنوات وتكون مسبوقة بشهادة البكالوريا اللبنانية-الجزء الثاني او ما يعادلها.\n- أو اجازة في العلوم الاقتصادية, بالاضافة الى شهادة تخصص في الاحصاء لا تقل مدة الدراسة لنيلها عن ثلاث سنوات.\n- أو شهادة الماجستير على الاقل او ما يعادلها في العلوم الاقتصادية او الاجتماعية بالاضافة الى شهادة تخصص في الاحصاء لا تقل مدة الدراسة لنيلها عن سنتين.\n- أو ان يكون المرشح عمل في وظيفة اختصاصي في العلوم الاقتصادية او الاجتماعية او الجغرافية او الديموغرافية او ادارة الاعمال في ادارة الاعمال في ادارة الاحصاء المركزي لمدة ست سنوات على الاقل, ونجح في دورة تدريبية في شؤون الاحصاء لا تقل مدتها عن ستة اشهر, يجريها المعهد الوطني للادارة والانماء في مجلس الخدمة المدنية وذلك بالاشتراك مع ادارة الاحصاء المركزي, ويعفى من الدورة التدريبية المذكورة, المرشح الذي يحمل شهادة تخصص في شؤون الاحصاء لا تقل مدة دراستها عن سنة."
        },
        {
          "type": "text",
          "data": "2- وظيفة اختصاصي في العلوم الاقتصادية او الاجتماعية او الجغرافية او الديموغرافية او ادارة الاعمال:"
        },
        {
          "type": "text",
          "data": "- اجازة في العلوم الاقتصادية او في العلوم الاجتماعية او في علم النفس او في الجغرافيا او في الديموغرافيا او في ادارة الاعمال, حصل عليها بعد نيل لبكالوريا اللبنانية - القسم الثاني - او ما يعادلها."
        },
        {
          "type": "text",
          "data": "3- وظيفة اختصاصي في الرياضيات الاحصائية:"
        },
        {
          "type": "text",
          "data": "اجازة في الرياضيات - تخصص احصاء - حصل عليها بعد نيل البكالوريا اللبنانية - القسم الثاني - او ما يعادلها."
        },
        {
          "type": "text",
          "data": "4- وظيفة موثق:"
        },
        {
          "type": "text",
          "data": "- شهادة جامعية في التوثيق لا تقل مدة الدراسة لنيلها عن ثلاث سنوات بعد البكالوريا اللبنانية -القسم الثاني- او ما يعادلها."
        },
        {
          "type": "text",
          "data": "- او اجازة في العلوم الاقتصادية او الاجتماعية او السياسية والادارية مع تخصص في التوثيق لمدة سنة على الاقل.\n- او ان يكون قد قضى في الخدمة الفعلية مدة لا تقل عن عشر سنوات بوظيفة موثق مساعد."
        },
        {
          "type": "text",
          "data": "5 - وظيفة موثق مساعد:"
        },
        {
          "type": "text",
          "data": "- شهادة البكالوريا المهنية - القسم الثاني - في التوثيق."
        },
        {
          "type": "text",
          "data": "6 - وظيفة احصائي مساعد:"
        },
        {
          "type": "text",
          "data": "- ان يجتاز بنجاح دورة اعدادية مدتها سنتان ينظمها مجلس الخدمة المدنية بالاشتراك مع ادارة الاحصاء المركزي اثر النجاح بمباراة للاشتراك في الدورة, على ان يكون المرشح حائزا على البكالوريا اللبنانية - القسم الثاني او ما يعادلها.\n- او شهادة الامتياز الفني في الاحصاء معترف بها رسميا تشتمل على دراسة نظرية وعملية في الاحصاء لمدة سنتين, حصل عليها بعد نيل البكالوريا اللبنانية - القسم الثاني - او ما يعادلها."
        },
        {
          "type": "text",
          "data": "7- وظيفة احصائي مساعد اول:"
        },
        {
          "type": "text",
          "data": "- ان يكون قد قضى في الخدمة الفعلية مدة ست سنوات على الاقل بوظيفة احصائي مساعد."
        },
        {
          "type": "text",
          "data": "8 - وظيفة محقق:"
        },
        {
          "type": "text",
          "data": "- شهادة البكالوريا اللبنانية - القسم الثاني - او ما يعادلها والنجاح في دورة تدريبية مدتها ثلاثة اشهر على الاقل يجريها المعهد الوطني للادارة والانماء في مجلس الخدمة المدنية وذلك بالاشتراك مع ادارة الاحصاء المركزي."
        },
        {
          "type": "text",
          "data": "9 - وظيفة محقق اول:"
        },
        {
          "type": "text",
          "data": "ان يكون قد امضى في الخدمة الفعلية مدة عشر سنوات على الاقل بوظيفة محقق في ادارة الاحصاء المركزي او في مديرية الاحصاء المركزي الملغاة."
        },
        {
          "type": "text",
          "data": "10- وظيفة محلل:"
        },
        {
          "type": "text",
          "data": "- شهادة الماجستير او الهندسة في المعلوماتية.\n- او الشروط المطلوبة لوظيفة احصائي بالاضافة الى النجاح في دورة تدريبية في طرق معالجة المعلومات, لا تقل مدتها عن ستة اشهر, يجريها المعهد الوطني للادارة والانماء في مجلس الخدمة المدنية وذلك بالاشتراك مع ادارة الاحصاء المركزي, ويعفى من الدورة التدريبية المذكورة, المرشح الذي يحمل شهادة تخصص في شؤون المعلوماتية لا تقل مدة دراستها عن سنة."
        },
        {
          "type": "text",
          "data": "11- وظيفة مبرمج:"
        },
        {
          "type": "text",
          "data": "- اجازة في المعلوماتية"
        },
        {
          "type": "text",
          "data": "- او شهادة الامتياز الفني - اختصاص المعلوماتية الادارية, مع خبرة ثلاث سنوات على الاقل.\n- أو شهادة جامعية في المعلوماتية لا تقل مدة الدراسة لنيلها عن السنتين بعد البكالوريا اللبنانية - القسم الثاني او ما يعادلها مع خبرة ثلاث سنوات على الاقل."
        },
        {
          "type": "text",
          "data": "12- وظيفة مبرمج محلل:"
        },
        {
          "type": "text",
          "data": "- اجازة في المعلوماتية\n- او ان يكون المرشح امضى في الخدمة الفعلية مدة ست سنوات على الاقل في وظيفة مبرمج في ملاك ادارة الاحصاء المركزي."
        },
        {
          "type": "text",
          "data": "13- وظيفة اختصاصي في تشغيل الحاسب الالكتروني:"
        },
        {
          "type": "text",
          "data": "- شهادة البكالوريا الفنية القسم الثاني (فرع برمجة الحاسبات الالكترونية) والنجاح في دورة تدريبية على تشغيل الحاسب الالكتروني يعدها مجلس الخدمة المدنية بالاشتراك مع ادارة الاحصاء المركزي."
        },
        {
          "type": "text",
          "data": "14- وظيفة مشرفة:"
        },
        {
          "type": "text",
          "data": "- ان تكون قد امضت في الخدمة الفعلية مدة ست سنوات على الاقل في وظيفة ثاقبة."
        },
        {
          "type": "text",
          "data": "15- وظيفة رئيس مشغل:"
        },
        {
          "type": "text",
          "data": "- ان يكون قد امضى في الخدمة الفعلية مدة عشر سنوات على الاقل باحدى وظيفتي مشرفة او اختصاصي في تشغيل الحاسب الالكتروني."
        },
        {
          "type": "text",
          "data": "16- وظيفة ثاقبة:"
        },
        {
          "type": "text",
          "data": "أ- تعدل تسمية وظيفة \"ثاقبة\" الملحوظة في ملاك رئاسة مجلس الوزراء-ادارة الاحصاء المركزي وتصبح \"مدخل معلومات\".\nب- تحدد الشروط الخاصة للتعيين في وظيفة \"مدخل معلومات\" المبينة في الفقرة الاولى اعلاه على الشكل التالي:\n- النجاح في دورة تدريبية على جهاز الحاسب الالكتروني يجريها المعهد الوطني للادارة والانماء في مجلس الخدمة المدنية وذلك بالاشتراك مع ادارة الاحصاء المركزي وبعد اختبار خاص يجري لهذه الغاية."
        },
        {
          "type": "text",
          "data": "17- وظيفة رسام:"
        },
        {
          "type": "text",
          "data": "- شهادة في الرسم من معهد معترف به رسميا."
        },
        {
          "type": "text",
          "data": "18- وظيفة رسام مصمم:"
        },
        {
          "type": "text",
          "data": "- ان يكون قد قضى في الخدمة الفعلية مدة عشر سنوات على الاقل بوظيفة رسام في ادارة الاحصاء المركزي او في مديرية الاحصاء المركزي الملغاة."
        }
      ]
    },
    {
      "number": "32",
      "content": [
        {
          "type": "text",
          "data": "يرفع الاحصائيون الى رتبة احصائي اول والمحللون الى رتبة محلل اول والاختصاصيون في العلوم الاقتصادية او الاجتماعية او الجغرافيا والديموغرافيا او ادارة الاعمال او الرياضيات الاحصائية الى رتبة اختصاصي اول والموثقون الى رتبة موثق اول وفاقا للشروط التالية:"
        },
        {
          "type": "text",
          "data": "- ان يكونوا بلغوا الدرجة الثانية من رتبتهم على الاقل."
        },
        {
          "type": "text",
          "data": "- وان يكونوا قد اجتازوا بنجاح دورة تدريبية خاصة ينظمها مجلس الخدمة المدنية بالاشتراك مع ادارة الاحصاء المركزي."
        },
        {
          "type": "text",
          "data": "- وان يكونوا قدموا بحثا حول موضوع معين او عمل احصائي او دراسة قاموا بها اثناء عملهم او ان يكونوا حائزين على شهادة الدكتوراه في اختصاص كل منهم."
        }
      ]
    },
    {
      "number": "33  (عدلت بموجب مرسوم 12805 / 1998) (عدلت بموجب مرسوم 7729 / 1995)",
      "content": [
        {
          "type": "text",
          "data": "تتولى لجنة يرئسها مدير عام ادارة الاحصاء المركزي ويكون اعضاؤها رؤساء المصالح الفنية في ادارة الاحصاء المركزي تقويم اعمال الموظفين المرشحين للترفيع وفقا للمادة 35 من هذا المرسوم."
        }
      ]
    },
    {
      "number": "34  مادة ملغاة  (الغيت بموجب مرسوم 7729 / 1995)",
      "content": [
        {
          "type": "text",
          "data": "يعين الاحصائي رئيس مصلحة بالاختيار من بين الاحصائيين اول ويجوز ايضا ان يعين رئيس مصلحة المركز الالي من بين المحللين اول."
        }
      ]
    },
    {
      "number": "35",
      "content": [
        {
          "type": "text",
          "data": "يرئس ادارة الاحصاء المركزي موظف من الفئة الاولى."
        }
      ]
    },
    {
      "number": "36",
      "content": [
        {
          "type": "text",
          "data": "يرئس مصلحة الديوان موظف من الفئة الثانية ويرئس كلا من الدوائر الادارة التابعة لهذه المصلحة موظف من الفئة الثالثة."
        }
      ]
    },
    {
      "number": "37",
      "content": [
        {
          "type": "text",
          "data": "يرئس كلا من المصالح الفنية الاخرى موظف برتبة احصائي رئيس مصلحة ويرئس كلا من الدوائر التابعة للمصالح الفنية والمكاتب الاقليمية التابعة لمصلحة العمليات الميدانية والاحصاءات الاقليمية موظف برتبة احصائي اول او احصائي باستثناء دائرة التوثيق التي يجوز ان يرئسها ايضا موظف برتبة موثق اول او موثق دائرة اداري وكل من دائرتي مصلحة المركز الالي التي يرئس كل منها موظف برتبة محلل اول او محلل او احصائي اول او احصائي."
        }
      ]
    },
    {
      "number": "38",
      "content": [
        {
          "type": "text",
          "data": "يرئس كلا من مشاغل دائرة العمل الالي موظف برتبة رئيس مشغل."
        }
      ]
    },
    {
      "number": "39",
      "content": [
        {
          "type": "text",
          "data": "يجوز نقل الثاقبات اللواتي امضين عشر سنوات او اكثر في الخدمة الفعلية الى وظيفة محقق او وظيفة كاتب او محرر شرط ان ينجحن في امتحان خاص يجريه مجلس الخدمة المدنية لهذه الغاية."
        }
      ]
    },
    {
      "number": "40",
      "content": [
        {
          "type": "text",
          "data": "تطبق على الموظفين الاداريين في ادارة الاحصاء المركزي ذات شروط التعيين المعمول بها في الوظائف المماثلة في الملاك الاداري العام."
        }
      ]
    },
    {
      "number": "41",
      "content": [
        {
          "type": "text",
          "data": "يحدد ملاك ادارة الاحصاء المركزي وفاقا للجدول رقم (1) الملحق بهذا المرسوم."
        }
      ]
    },
    {
      "number": "42",
      "content": [
        {
          "type": "text",
          "data": "تحدد فئات ورتب وسلسلة رواتب الموظفين الفنيين في ادارة الاحصاء المركزي وفاقا للجدول رقم (2) الملحق بهذا المرسوم. وتطبق على الموظفين الاداريين في ادارة الاحصاء المركزي سلسلة الرتب والرواتب المعمول بها في الوظائف المماثلة في الملاك الاداري العام."
        }
      ]
    },
    {
      "number": "43",
      "content": [
        {
          "type": "text",
          "data": "يعطى الاحصائيون رؤساء مصالح والاحصائيون اول والاحصائيون والمحللون اول والمحللون التابعون لادارة الاحصاء المركزي الذين تتوفر فيهم الشروط الخاصة المنصوص عليها في هذا المرسوم, التعويض الخاص المنصوص عنه في الفقرة الاولى من المادة 22 من المرسوم الاشتراعي رقم 112 تاريخ 12/6/1959 وتحسب مدة خدمات الذين كانوا يعملون في مديرية لاحصاء المركزي بوزارة التصميم العام الملغاة وتتوفر فيهم الشروط المار ذكرها كخدمات فعلية تدخل لحساب النسبة المئوية لهذا التعويض ."
        },
        {
          "type": "text",
          "data": "اما الاحصائيون الذين لا تتوفر فيهم الشروط الخاصة الجديدة المنصوص عليها في هذا المرسوم فيثبرون على تقاضي التعويض المنصوص عليه في المادة 49 من القانون الصادر بتاريخ 12/6/1962 المتعلق بتنظيم وزارة التصميم العام."
        }
      ]
    },
    {
      "number": "44",
      "content": [
        {
          "type": "text",
          "data": "يحتفظ مدير عام ادارة الاحصاء المركزي الذي يعين من بين الاحصائيين رؤساء مصالح او الاحصائيين اول او المحللين اول التابعين لادارة الاحصاء المركزي بالتعويض الخاص الدذي يتقاضاه وفقا لاحكام المادة السابقة من هذا المرسوم."
        }
      ]
    },
    {
      "number": "59  ينشر هذا المرسوم ويبلغ حيث تدعو الحاجة ويعمل به فور نشره في الجريدة الرسمية.",
      "content": [
        {
          "type": "text",
          "data": "تعطى فئات الموظفين في الملاك الدائم في ادارة الاحصاء المركزي المبينة ادناه تعويضا خاصا قدره عشرون بالمئة من الراتب الاساسي (20 %):"
        },
        {
          "type": "text",
          "data": "1- الاختصاصيون اول والاختصاصيون في الرياضيات الاحصائية."
        },
        {
          "type": "text",
          "data": "2- الاختصاصيون اول والاختصاصيون في العلوم الاقتصادية او الاجتماعية او في الجغرافيا. او في ادارة الاعمال الذين حصلوا على شهادة في الاحصاء لا تقل مدة الدراسة لنيلها عن سنتين كاملتين."
        },
        {
          "type": "text",
          "data": "3- الاحصائيون المساعدون اول والاحصائيون المساعدون."
        }
      ]
    },
    {
      "number": "45",
      "content": [
        {
          "type": "text",
          "data": "يمكن اعطاء موظفي ادارة الاحصاء المركزي الذين لا يتقاضون تعويض نقل شهري مقطوع ويتطلب عملهم النزول الى الميدان للاعمال المتعلقة بتنفيذ التحقيقات الاحصائية تعويض نقل مقطوع عن كل يوم عمل فعلي في الميدان يحدد مقداره بمرسوم يتخذ في مجلس الوزراء بعد موافقة مجلس الخدمة المدنية."
        },
        {
          "type": "text",
          "data": "وينظم رئيس المصلحة المختص جدولا شهريا بالتعويضات المستحقة لكل من موظفيه يصرف بعد موافقة مدير عام ادارة الاحصاء المركزي."
        }
      ]
    },
    {
      "number": "46",
      "content": [
        {
          "type": "text",
          "data": "يجوز اعطاء رؤساء المصالح والاحصائيين اول والاحصائيين تعويض نقل وانتقال شهري مقطوع يحدد مقداره وشروط اعطائه بمرسوم يتخذ في مجلس الوزراء بعد موافقة مجلس الخدمة المدنية."
        }
      ]
    },
    {
      "number": "47",
      "content": [
        {
          "type": "text",
          "data": "يحق لادارة الاحصاء المركزي, عندما تدعو الحاجة, الاستعانة باشخاص من خارج الادارة لتنفيذ مختلف الاعمال الاحصائية, في الميدان او في المكتب وتحدد بقرار من مدير عام ادارة الاحصاء المركزي المؤهلات اللازمة لهؤلاء الاشخاص وبدل الاتعاب عن كل وحدة عمل منفذة ومقبولة."
        }
      ]
    },
    {
      "number": "48",
      "content": [
        {
          "type": "text",
          "data": "يحق لمدير عام ادارة الاحصاء المركزي ان يعدل دوام عمل المصالح المكلفة بدراسة وتنفيذ التحقيقات الاحصائية الهامة بحيث يكون العمل قبل الظهر وبعده على ان يتقاضى الموظفون الذين يشملهم القرار زيادة نسبية على رواتبهم تعويضاتهم توازي نسبة ساعات العمل المطلوب تأمينها زيادة عن الدوام العادي على ان لا تزيد نسبة الزيادة عن 20 % من الراتب بما فيه التعويض الخاص المنصوص عليه في المادتين 46 و48 من هذا المرسوم."
        }
      ]
    },
    {
      "number": "49",
      "content": [
        {
          "type": "text",
          "data": "يمكن اعطاء موظفي مصلحة المركز الالي العاملين على الالات والمشرفين التسلسليين عليهم مكافأة انتاج تحدد اسس اعطائها ومقدارها بقرار من المدير العام بناء على اقتراح رئيس المركز الالي."
        }
      ]
    },
    {
      "number": "50",
      "content": [
        {
          "type": "text",
          "data": "يمكن اعطاء المحققين اول والمحققين اثناء القيام باعمالهم والمشرفين التسلسيين عليه مكافأة انتاج عن اعمال يمكن قياسها بعدد استمارات او وحدات اخرى منفذة, وتحدد اسس اعطاء المكافأة ومقدارها بقرار من المدير العام بناء على اقتراح رئيس المصلحة المختص ."
        }
      ]
    },
    {
      "number": "51",
      "content": [
        {
          "type": "text",
          "data": "يصنف الاخصائيون رؤساء المصالح في مديرية الاحصاء المركزي بوزارة التصميم العام الملغاة بوظيفة احصائي رئيس مصلحة دون ان يؤدي هذا التصنيف الى اي تعديل في الراتب ويحتفظون باقدميتهم المؤهلة للتدرج."
        },
        {
          "type": "text",
          "data": "يتم التصنيف والتوزيع على المصالح الفنية المستحدثة في ادارة الاحصاء المركزي, بمرسوم بناء على اقتراح رئيس مجلس الوزراء بعد موافقة مجلس الخدمة المدينة."
        }
      ]
    },
    {
      "number": "52",
      "content": [
        {
          "type": "text",
          "data": "يصنف الاحصائيون رؤساء دوائر والاحصائيون في مديرية الاحصاء المركزي بوزارة التصميم العام الملغاة بوظيفة احصائي بالدرجة التي توازي الدرجة التي يشغلونها حاليا ويحتفظون باقدمتهم المؤهلة للتدرج."
        },
        {
          "type": "text",
          "data": "يتم التصنيف بمرسوم بناء على اقتراح رئيس مجلس الوزراء بعد موافقة مجلس الخدمة المدنية."
        }
      ]
    },
    {
      "number": "53",
      "content": [
        {
          "type": "text",
          "data": "يصنف موظفو مديرية الاحصاء المركزي في وزارة التصميم العام الملغاة المذكورة وظائفهم ادناه في الوظيفة المبينة تجاه كل منها, دون ان يؤدي هذا التصنيف الى اي تعديل في الفئة والراتب , ويحتفظون بحقهم في القدم المؤهل للتدرج:"
        },
        {
          "type": "text",
          "data": "الوظيفة القديمة الوظيفة الجديدة"
        },
        {
          "type": "text",
          "data": "اخصائي في التخطيط الالي اختصاصي في تشغيل الحاسب الالكتروني محقق محقق ثاقبة وواضعة رموز ثاقبة يتم التصنيف بمرسوم بناء على اقتراح رئيس مجلس الوزراء بعد موافقة مجلس الخدمة المدنية."
        }
      ]
    },
    {
      "number": "54",
      "content": [
        {
          "type": "text",
          "data": "يصنف الموظفون في مديرية الاحصاء المركزي في وزارة التصميم العام الملغاة غير الواردة ذكرهم في المواد السابقة من هذا المرسوم بالوظائف المماثلة لوظائفهم السابقة دون ان يؤدي ذلك الى اي تعديل في الفئة والرتبة والراتب ويحتفظون باقدميتهم المؤهلة للتدرج. يتم التصنيف بمرسوم بناء على اقتراح رئيس مجلس الوزراء بعد موافقة مجلس الخدمة المدنية."
        }
      ]
    },
    {
      "number": "59  ينشر هذا المرسوم ويبلغ حيث تدعو الحاجة ويعمل به فور نشره في الجريدة الرسمية.",
      "content": [
        {
          "type": "text",
          "data": "ينشر هذا المرسوم ويبلغ حيث تدعو الحاجة ويعمل به فور نشره في الجريدة الرسمية."
        }
      ]
    }
  ],
  "signature": "بعبدا في 28 شابط 1980\nالامضاء: الياس  سركيس\nصدر عن رئيس  الجمهورية\nرئيس  مجلس  الوزراء\nالامضاء: سليم الحص\nرئيس  مجلس  وزراء\nالامضاء: سليم الحص\nوزير المالية\nالامضاء: علي الخليل"
}